st_review_component/__init__.py
st_review_component/frontend/build/asset-manifest.json
st_review_component/frontend/build/bootstrap.min.css
st_review_component/frontend/build/index.html
st_review_component/frontend/build/static/css/main.9960d55a.css
st_review_component/frontend/build/static/css/main.9960d55a.css.map
st_review_component/frontend/build/static/css/main.af311eb4.css
st_review_component/frontend/build/static/css/main.af311eb4.css.map
st_review_component/frontend/build/static/js/main.a606668a.js
st_review_component/frontend/build/static/js/main.a606668a.js.LICENSE.txt
st_review_component/frontend/build/static/js/main.a606668a.js.map
st_review_component/frontend/build/static/js/main.ed936025.js
st_review_component/frontend/build/static/js/main.ed936025.js.LICENSE.txt
st_review_component/frontend/build/static/js/main.ed936025.js.map
st_review_component-0.0.4.dist-info/LICENSE
st_review_component-0.0.4.dist-info/METADATA
st_review_component-0.0.4.dist-info/WHEEL
st_review_component-0.0.4.dist-info/top_level.txt
st_review_component-0.0.4.dist-info/RECORD
